hyypns.py
hyypns-0.1.5.dist-info/LICENSE.txt
hyypns-0.1.5.dist-info/METADATA
hyypns-0.1.5.dist-info/WHEEL
hyypns-0.1.5.dist-info/top_level.txt
hyypns-0.1.5.dist-info/RECORD
