Metadata-Version: 2.2
Name: hyypns
Version: 0.1.5
Summary: hyypns
Author: huang yi yi
Author-email: 363766687@qq.com
Requires-Python: >=3.6
License-File: LICENSE.txt
Requires-Dist: pyfiglet>=1.0.1.post1
Requires-Dist: requests>=2.32.2.post1
Requires-Dist: Cython>=3.0.11
Requires-Dist: setuptools>=75.7.0
Requires-Dist: pillow>=11.0.0
Requires-Dist: WMI>=1.5
Requires-Dist: docker>=7.0.0
Requires-Dist: puautogui>=0.9.53
Dynamic: author
Dynamic: author-email
Dynamic: description
Dynamic: requires-dist
Dynamic: requires-python
Dynamic: summary
